cutejoe/__init__.py
cutejoe/commands/__init__.py
cutejoe/commands/changelog.py
cutejoe/commands/config_file.py
cutejoe/helpers/__init__.py
cutejoe/helpers/changelog.py
cutejoe/helpers/utils.py
cutejoe/helpers/configurations/.default_config.yml
cutejoe/helpers/configurations/__init__.py
cutejoe/helpers/configurations/base.py
cutejoe/helpers/configurations/config_v1.py
CuteJoe-0.1.1.dist-info/LICENSE
CuteJoe-0.1.1.dist-info/METADATA
CuteJoe-0.1.1.dist-info/WHEEL
CuteJoe-0.1.1.dist-info/entry_points.txt
CuteJoe-0.1.1.dist-info/top_level.txt
CuteJoe-0.1.1.dist-info/RECORD
