Metadata-Version: 2.1
Name: CuteJoe
Version: 0.1.1
Summary: Commands to automate some release tasks
Home-page: https://github.com/MatheusBrochi/CuteJoe
Author: MatheusBrochi
Author-email: matheusgbrochi@gmail.com
License: MIT License
Project-URL: Changelog, https://github.com/MatheusBrochi/CuteJoe/tree/master/changelogs
Project-URL: Issue Tracker, https://github.com/MatheusBrochi/CuteJoe/issues
Platform: UNKNOWN
Classifier: Development Status :: 3 - Alpha
Classifier: Environment :: Console
Classifier: Intended Audience :: Developers
Classifier: Intended Audience :: System Administrators
Classifier: Programming Language :: Python :: 2
Classifier: Programming Language :: Python :: 3
Classifier: License :: OSI Approved :: MIT License
Classifier: Topic :: Software Development :: Documentation
Requires-Dist: Click (~=7.0)
Requires-Dist: PyYAML (~=5.1.2)
Provides-Extra: test
Requires-Dist: pytest ; extra == 'test'
Requires-Dist: pytest-flake8 ; extra == 'test'
Requires-Dist: pytest-cov ; extra == 'test'
